MCTS/DFMCS.py
MCTS/MCTS.py
MCTS/__init__.py
MCTS/integrate.py
MCTS/net.py
MCTS/test.py
MCTS/utils.py
MCTS_DUT/DFMCS.py
MCTS_DUT/MCTS.py
MCTS_DUT/__init__.py
MCTS_DUT/integrate.py
MCTS_DUT/net.py
MCTS_DUT/test.py
MCTS_DUT/utils.py
dut-sar/DFMCS.py
dut-sar/MCTS.py
dut-sar/__init__.py
dut-sar/integrate.py
dut-sar/net.py
dut-sar/test.py
dut-sar/utils.py
dut_sar-1.1.1.dist-info/LICENSE
dut_sar-1.1.1.dist-info/METADATA
dut_sar-1.1.1.dist-info/WHEEL
dut_sar-1.1.1.dist-info/top_level.txt
dut_sar-1.1.1.dist-info/RECORD
